gitignore_maker/__init__.py
gitignore_maker/constants.py
gitignore_maker/main.py
gitignore_maker/gitignore/AL.gitignore
gitignore_maker/gitignore/Actionscript.gitignore
gitignore_maker/gitignore/Ada.gitignore
gitignore_maker/gitignore/Agda.gitignore
gitignore_maker/gitignore/Android.gitignore
gitignore_maker/gitignore/AppEngine.gitignore
gitignore_maker/gitignore/AppceleratorTitanium.gitignore
gitignore_maker/gitignore/ArchLinuxPackages.gitignore
gitignore_maker/gitignore/Autotools.gitignore
gitignore_maker/gitignore/Ballerina.gitignore
gitignore_maker/gitignore/C++.gitignore
gitignore_maker/gitignore/C.gitignore
gitignore_maker/gitignore/CFWheels.gitignore
gitignore_maker/gitignore/CMake.gitignore
gitignore_maker/gitignore/CONTRIBUTING.md
gitignore_maker/gitignore/CUDA.gitignore
gitignore_maker/gitignore/CakePHP.gitignore
gitignore_maker/gitignore/ChefCookbook.gitignore
gitignore_maker/gitignore/Clojure.gitignore
gitignore_maker/gitignore/CodeIgniter.gitignore
gitignore_maker/gitignore/CommonLisp.gitignore
gitignore_maker/gitignore/Composer.gitignore
gitignore_maker/gitignore/Concrete5.gitignore
gitignore_maker/gitignore/Coq.gitignore
gitignore_maker/gitignore/CraftCMS.gitignore
gitignore_maker/gitignore/D.gitignore
gitignore_maker/gitignore/DM.gitignore
gitignore_maker/gitignore/Dart.gitignore
gitignore_maker/gitignore/Delphi.gitignore
gitignore_maker/gitignore/Drupal.gitignore
gitignore_maker/gitignore/EPiServer.gitignore
gitignore_maker/gitignore/Eagle.gitignore
gitignore_maker/gitignore/Elisp.gitignore
gitignore_maker/gitignore/Elixir.gitignore
gitignore_maker/gitignore/Elm.gitignore
gitignore_maker/gitignore/Erlang.gitignore
gitignore_maker/gitignore/ExpressionEngine.gitignore
gitignore_maker/gitignore/ExtJs.gitignore
gitignore_maker/gitignore/Fancy.gitignore
gitignore_maker/gitignore/Finale.gitignore
gitignore_maker/gitignore/FlaxEngine.gitignore
gitignore_maker/gitignore/ForceDotCom.gitignore
gitignore_maker/gitignore/Fortran.gitignore
gitignore_maker-0.1.3.dist-info/LICENSE
gitignore_maker-0.1.3.dist-info/METADATA
gitignore_maker-0.1.3.dist-info/WHEEL
gitignore_maker-0.1.3.dist-info/entry_points.txt
gitignore_maker-0.1.3.dist-info/top_level.txt
gitignore_maker-0.1.3.dist-info/RECORD
