Metadata-Version: 2.1
Name: gitignore-maker
Version: 0.1.3
Summary: A powerful command-line tool for managing .gitignore files with language-specific templates and size-based filtering.
Home-page: https://github.com/Eemayas/gitignore_maker
Author: Eemayas
Author-email: prashantmanandhar2002@gmail.com
Classifier: Programming Language :: Python :: 3
Classifier: License :: OSI Approved :: MIT License
Classifier: Operating System :: OS Independent
Requires-Python: >=3.6
License-File: LICENSE
